ilog/__init__.py
ilog/constants.py
ilog/decorators.py
ilog/defaults.py
ilog/indented_logger.py
ilog/setup.py
ilog/utils.py
indelog-1.0.0.dist-info/licenses/LICENSE
indelog-1.0.0.dist-info/METADATA
indelog-1.0.0.dist-info/WHEEL
indelog-1.0.0.dist-info/top_level.txt
indelog-1.0.0.dist-info/RECORD
