Metadata-Version: 2.4
Name: indelog
Version: 1.0.0
Summary: An extension of the standard logging package with indentation, severity coloring, default formatting and saving, trace level.
Author-email: Peter Gee <petergee302@gmail.com>
License: MIT
Keywords: logging,indentation,tracing
Requires-Python: >=3.10
License-File: LICENSE
Provides-Extra: dev
Requires-Dist: pyright; extra == "dev"
Requires-Dist: pytest; extra == "dev"
Provides-Extra: publish
Requires-Dist: setuptools; extra == "publish"
Requires-Dist: build; extra == "publish"
Requires-Dist: twine; extra == "publish"
Dynamic: license-file
